bqtables/__init__.py
bqtables/client.py
bqtables-0.9.15.dist-info/LICENSE
bqtables-0.9.15.dist-info/METADATA
bqtables-0.9.15.dist-info/WHEEL
bqtables-0.9.15.dist-info/top_level.txt
bqtables-0.9.15.dist-info/RECORD
