Metadata-Version: 2.1
Name: bqtables
Version: 0.9.15
Summary: Wraps the Google Cloud API with a class designed for easy streaming inserts and updates.
Home-page: https://github.com/sethlivingston/python-bq-client
Author: Seth M. Livingston
Author-email: webdevbyseth@gmail.com
License: MIT
Platform: UNKNOWN
Classifier: License :: OSI Approved :: MIT License
Classifier: Programming Language :: Python :: 3
Classifier: Programming Language :: Python :: 3.7
Requires-Dist: google-cloud-bigquery
